ssb_libtest8/__init__.py
ssb_libtest8/__main__.py
ssb_libtest8/functions.py
ssb_libtest8/py.typed
ssb_libtest8-0.0.1.dist-info/LICENSE
ssb_libtest8-0.0.1.dist-info/METADATA
ssb_libtest8-0.0.1.dist-info/WHEEL
ssb_libtest8-0.0.1.dist-info/entry_points.txt
ssb_libtest8-0.0.1.dist-info/RECORD
